[
    {
        "equipoLocal": {"id": 440},
        "equipoVisitante": {"id": 450},
        "golesLocal": 2,
        "golesVisitante": 1
    },
    {
        "equipoLocal": {"id": 450},
        "equipoVisitante": {"id": 441},
        "golesLocal": 1,
        "golesVisitante": 3
    },
    {
        "equipoLocal": {"id": 436},
        "equipoVisitante": {"id": 450},
        "golesLocal": 2,
        "golesVisitante": 1
    },
    {
        "equipoLocal": {"id": 452},
        "equipoVisitante": {"id": 450},
        "golesLocal": 0,
        "golesVisitante": 0
    },
    {
        "equipoLocal": {"id": 450},
        "equipoVisitante": {"id": 460},
        "golesLocal": 0,
        "golesVisitante": 0
    },
    {
        "equipoLocal": {"id": 457},
        "equipoVisitante": {"id": 450},
        "golesLocal": 0,
        "golesVisitante": 1
    },
    {
        "equipoLocal": {"id": 450},
        "equipoVisitante": {"id": 434},
        "golesLocal": 0,
        "golesVisitante": 0
    },
    {
        "equipoLocal": {"id": 450},
        "equipoVisitante": {"id": 439},
        "golesLocal": 0,
        "golesVisitante": 1
    },
    {
        "equipoLocal": {"id": 450},
        "equipoVisitante": {"id": 452},
        "golesLocal": 1,
        "golesVisitante": 2
    },
    {
        "equipoLocal": {"id": 459},
        "equipoVisitante": {"id": 450},
        "golesLocal": 1,
        "golesVisitante": 1
    },
    {
        "equipoLocal": {"id": 450},
        "equipoVisitante": {"id": 446},
        "golesLocal": 0,
        "golesVisitante": 2
    },
    {
        "equipoLocal": {"id": 439},
        "equipoVisitante": {"id": 450},
        "golesLocal": 0,
        "golesVisitante": 1
    },
    {
        "equipoLocal": {"id": 441},
        "equipoVisitante": {"id": 450},
        "golesLocal": 2,
        "golesVisitante": 0
    },
    {
        "equipoLocal": {"id": 450},
        "equipoVisitante": {"id": 445},
        "golesLocal": 2,
        "golesVisitante": 1
    },
    {
        "equipoLocal": {"id": 434},
        "equipoVisitante": {"id": 450},
        "golesLocal": 2,
        "golesVisitante": 1
    },
    {
        "equipoLocal": {"id": 450},
        "equipoVisitante": {"id": 457},
        "golesLocal": 3,
        "golesVisitante": 0
    },
    {
        "equipoLocal": {"id": 453},
        "equipoVisitante": {"id": 450},
        "golesLocal": 1,
        "golesVisitante": 2
    },
    {
        "equipoLocal": {"id": 450},
        "equipoVisitante": {"id": 455},
        "golesLocal": 0,
        "golesVisitante": 0
    },
    {
        "equipoLocal": {"id": 451},
        "equipoVisitante": {"id": 450},
        "golesLocal": 0,
        "golesVisitante": 1
    },
    {
        "equipoLocal": {"id": 450},
        "equipoVisitante": {"id": 456},
        "golesLocal": 1,
        "golesVisitante": 0
    },
    {
        "equipoLocal": {"id": 1064},
        "equipoVisitante": {"id": 450},
        "golesLocal": 1,
        "golesVisitante": 2
    },
    {
        "equipoLocal": {"id": 450},
        "equipoVisitante": {"id": 438},
        "golesLocal": 2,
        "golesVisitante": 0
    },
    {
        "equipoLocal": {"id": 442},
        "equipoVisitante": {"id": 450},
        "golesLocal": 1,
        "golesVisitante": 1
    },
    {
        "equipoLocal": {"id": 450},
        "equipoVisitante": {"id": 449},
        "golesLocal": 1,
        "golesVisitante": 0
    },
    {
        "equipoLocal": {"id": 450},
        "equipoVisitante": {"id": 2432},
        "golesLocal": 5,
        "golesVisitante": 2
    },
    {
        "equipoLocal": {"id": 448},
        "equipoVisitante": {"id": 450},
        "golesLocal": 1,
        "golesVisitante": 0
    },
    {
        "equipoLocal": {"id": 450},
        "equipoVisitante": {"id": 460},
        "golesLocal": 1,
        "golesVisitante": 1
    },
    {
        "equipoLocal": {"id": 450},
        "equipoVisitante": {"id": 1065},
        "golesLocal": 1,
        "golesVisitante": 1
    },
    {
        "equipoLocal": {"id": 437},
        "equipoVisitante": {"id": 450},
        "golesLocal": 0,
        "golesVisitante": 0
    },
    {
        "equipoLocal": {"id": 450},
        "equipoVisitante": {"id": 436},
        "golesLocal": 0,
        "golesVisitante": 0
    },
    {
        "equipoLocal": {"id": 435},
        "equipoVisitante": {"id": 450},
        "golesLocal": 3,
        "golesVisitante": 1
    },
    {
        "equipoLocal": {"id": 450},
        "equipoVisitante": {"id": 440},
        "golesLocal": 4,
        "golesVisitante": 0
    },
    {
        "equipoLocal": {"id": 458},
        "equipoVisitante": {"id": 450},
        "golesLocal": 2,
        "golesVisitante": 3
    },
    {
        "equipoLocal": {"id": 450},
        "equipoVisitante": {"id": 1960},
        "golesLocal": 3,
        "golesVisitante": 0
    },
    {
        "equipoLocal": {"id": 2348},
        "equipoVisitante": {"id": 450},
        "golesLocal": 3,
        "golesVisitante": 2
    },
    {
        "equipoLocal": {"id": 455},
        "equipoVisitante": {"id": 450},
        "golesLocal": 1,
        "golesVisitante": 1
    },
    {
        "equipoLocal": {"id": 450},
        "equipoVisitante": {"id": 474},
        "golesLocal": 1,
        "golesVisitante": 1
    },
    {
        "equipoLocal": {"id": 478},
        "equipoVisitante": {"id": 450},
        "golesLocal": 0,
        "golesVisitante": 0
    },
    {
        "equipoLocal": {"id": 450},
        "equipoVisitante": {"id": 1153},
        "golesLocal": 2,
        "golesVisitante": 0
    },
    {
        "equipoLocal": {"id": 3707},
        "equipoVisitante": {"id": 450},
        "golesLocal": 0,
        "golesVisitante": 1
    },
    {
        "equipoLocal": {"id": 450},
        "equipoVisitante": {"id": 10491},
        "golesLocal": 4,
        "golesVisitante": 0
    },
    {
        "equipoLocal": {"id": 794},
        "equipoVisitante": {"id": 450},
        "golesLocal": 0,
        "golesVisitante": 0
    },
    {
        "equipoLocal": {"id": 10491},
        "equipoVisitante": {"id": 450},
        "golesLocal": 0,
        "golesVisitante": 4
    },
    {
        "equipoLocal": {"id": 450},
        "equipoVisitante": {"id": 794},
        "golesLocal": 1,
        "golesVisitante": 1
    },
    {
        "equipoLocal": {"id": 450},
        "equipoVisitante": {"id": 3707},
        "golesLocal": 4,
        "golesVisitante": 0
    },
    {
        "equipoLocal": {"id": 464},
        "equipoVisitante": {"id": 450},
        "golesLocal": 0,
        "golesVisitante": 1
    },
    {
        "equipoLocal": {"id": 1152},
        "equipoVisitante": {"id": 450},
        "golesLocal": 2,
        "golesVisitante": 1
    },
    {
        "equipoLocal": {"id": 450},
        "equipoVisitante": {"id": 1152},
        "golesLocal": 4,
        "golesVisitante": 0
    },
    {
        "equipoLocal": {"id": 450},
        "equipoVisitante": {"id": 151},
        "golesLocal": 3,
        "golesVisitante": 0
    },
    {
        "equipoLocal": {"id": 151},
        "equipoVisitante": {"id": 450},
        "golesLocal": 0,
        "golesVisitante": 2
    },
    {
        "equipoLocal": {"id": 131},
        "equipoVisitante": {"id": 450},
        "golesLocal": 1,
        "golesVisitante": 0
    },
    {
        "equipoLocal": {"id": 450},
        "equipoVisitante": {"id": 131},
        "golesLocal": 1,
        "golesVisitante": 0
    },
    {
        "equipoLocal": {"id": 453},
        "equipoVisitante": {"id": 450},
        "golesLocal": 1,
        "golesVisitante": 1
    },
    {
        "equipoLocal": {"id": 445},
        "equipoVisitante": {"id": 450},
        "golesLocal": 0,
        "golesVisitante": 2
    }
]