[{
    "resultadoPartido": {
      "partido": {
        "local": {
          "nombre": "Gimnasia L.P."
        },
        "visitante": {
          "nombre": "Platense"
        }
      },
      "resultado": {
        "marcadorPorEquipo": {
          "Gimnasia L.P.": 1,
          "Platense": 1
        }
      }
    }
  },
  {
    "resultadoPartido": {
      "partido": {
        "local": {
          "nombre": "Gimnasia L.P."
        },
        "visitante": {
          "nombre": "Talleres Cordoba"
        }
      },
      "resultado": {
        "marcadorPorEquipo": {
          "Gimnasia L.P.": 2,
          "Talleres Cordoba": 2
        }
      }
    }
  },
  {
    "resultadoPartido": {
      "partido": {
        "local": {
          "nombre": "Gimnasia L.P."
        },
        "visitante": {
          "nombre": "Boca Juniors"
        }
      },
      "resultado": {
        "marcadorPorEquipo": {
          "Gimnasia L.P.": 1,
          "Boca Juniors": 3
        }
      }
    }
  },
  {
    "resultadoPartido": {
      "partido": {
        "local": {
          "nombre": "Gimnasia L.P."
        },
        "visitante": {
          "nombre": "Atletico Tucuman"
        }
      },
      "resultado": {
        "marcadorPorEquipo": {
          "Gimnasia L.P.": 0,
          "Atletico Tucuman": 2
        }
      }
    }
  },
  {
    "resultadoPartido": {
      "partido": {
        "local": {
          "nombre": "Gimnasia L.P."
        },
        "visitante": {
          "nombre": "Independiente"
        }
      },
      "resultado": {
        "marcadorPorEquipo": {
          "Gimnasia L.P.": 1,
          "Independiente": 1
        }
      }
    }
  },
  {
    "resultadoPartido": {
      "partido": {
        "local": {
          "nombre": "Gimnasia L.P."
        },
        "visitante": {
          "nombre": "Newells Old Boys"
        }
      },
      "resultado": {
        "marcadorPorEquipo": {
          "Gimnasia L.P.": 2,
          "Newells Old Boys": 2
        }
      }
    }
  },
  {
    "resultadoPartido": {
      "partido": {
        "local": {
          "nombre": "Gimnasia L.P."
        },
        "visitante": {
          "nombre": "Central Cordoba de Santiago"
        }
      },
      "resultado": {
        "marcadorPorEquipo": {
          "Gimnasia L.P.": 0,
          "Central Cordoba de Santiago": 0
        }
      }
    }
  },
  {
    "resultadoPartido": {
      "partido": {
        "local": {
          "nombre": "Gimnasia L.P."
        },
        "visitante": {
          "nombre": "Huracan"
        }
      },
      "resultado": {
        "marcadorPorEquipo": {
          "Gimnasia L.P.": 1,
          "Huracan": 0
        }
      }
    }
  },
  {
    "resultadoPartido": {
      "partido": {
        "local": {
          "nombre": "Gimnasia L.P."
        },
        "visitante": {
          "nombre": "Union Santa Fe"
        }
      },
      "resultado": {
        "marcadorPorEquipo": {
          "Gimnasia L.P.": 0,
          "Union Santa Fe": 2
        }
      }
    }
  },
  {
    "resultadoPartido": {
      "partido": {
        "local": {
          "nombre": "Gimnasia L.P."
        },
        "visitante": {
          "nombre": "Sarmiento Junin"
        }
      },
      "resultado": {
        "marcadorPorEquipo": {
          "Gimnasia L.P.": 0,
          "Sarmiento Junin": 0
        }
      }
    }
  },
  {
    "resultadoPartido": {
      "partido": {
        "local": {
          "nombre": "Gimnasia L.P."
        },
        "visitante": {
          "nombre": "Godoy Cruz"
        }
      },
      "resultado": {
        "marcadorPorEquipo": {
          "Gimnasia L.P.": 0,
          "Godoy Cruz": 2
        }
      }
    }
  },
  {
    "resultadoPartido": {
      "partido": {
        "local": {
          "nombre": "Gimnasia L.P."
        },
        "visitante": {
          "nombre": "Lanus"
        }
      },
      "resultado": {
        "marcadorPorEquipo": {
          "Gimnasia L.P.": 1,
          "Lanus": 0
        }
      }
    }
  },
  {
    "resultadoPartido": {
      "partido": {
        "local": {
          "nombre": "Gimnasia L.P."
        },
        "visitante": {
          "nombre": "Arsenal Sarandi"
        }
      },
      "resultado": {
        "marcadorPorEquipo": {
          "Gimnasia L.P.": 1,
          "Arsenal Sarandi": 0
        }
      }
    }
  },
  {
    "resultadoPartido": {
      "partido": {
        "local": {
          "nombre": "Gimnasia L.P."
        },
        "visitante": {
          "nombre": "Tigre"
        }
      },
      "resultado": {
        "marcadorPorEquipo": {
          "Gimnasia L.P.": 1,
          "Tigre": 1
        }
      }
    }
  },
  {
    "resultadoPartido": {
      "partido": {
        "local": {
          "nombre": "Gimnasia L.P."
        },
        "visitante": {
          "nombre": "Argentinos JRS"
        }
      },
      "resultado": {
        "marcadorPorEquipo": {
          "Gimnasia L.P.": 4,
          "Argentinos JRS": 2
        }
      }
    }
  },
  {
    "resultadoPartido": {
      "partido": {
        "local": {
          "nombre": "Gimnasia L.P."
        },
        "visitante": {
          "nombre": "Belgrano Cordoba"
        }
      },
      "resultado": {
        "marcadorPorEquipo": {
          "Gimnasia L.P.": 0,
          "Belgrano Cordoba": 2
        }
      }
    }
  },
  {
    "resultadoPartido": {
      "partido": {
        "local": {
          "nombre": "Gimnasia L.P."
        },
        "visitante": {
          "nombre": "River Plate"
        }
      },
      "resultado": {
        "marcadorPorEquipo": {
          "Gimnasia L.P.": 0,
          "River Plate": 3
        }
      }
    }
  },
  {
    "resultadoPartido": {
      "partido": {
        "local": {
          "nombre": "Gimnasia L.P."
        },
        "visitante": {
          "nombre": "Racing Club"
        }
      },
      "resultado": {
        "marcadorPorEquipo": {
          "Gimnasia L.P.": 3,
          "Racing Club": 1
        }
      }
    }
  },
  {
    "resultadoPartido": {
      "partido": {
        "local": {
          "nombre": "Gimnasia L.P."
        },
        "visitante": {
          "nombre": "Rosario Central"
        }
      },
      "resultado": {
        "marcadorPorEquipo": {
          "Gimnasia L.P.": 1,
          "Rosario Central": 3
        }
      }
    }
  },
  {
    "resultadoPartido": {
      "partido": {
        "local": {
          "nombre": "Gimnasia L.P."
        },
        "visitante": {
          "nombre": "Estudiantes L.P."
        }
      },
      "resultado": {
        "marcadorPorEquipo": {
          "Gimnasia L.P.": 2,
          "Estudiantes L.P.": 1
        }
      }
    }
  },
  {
    "resultadoPartido": {
      "partido": {
        "local": {
          "nombre": "Gimnasia L.P."
        },
        "visitante": {
          "nombre": "San Lorenzo"
        }
      },
      "resultado": {
        "marcadorPorEquipo": {
          "Gimnasia L.P.": 0,
          "San Lorenzo": 4
        }
      }
    }
  },
  {
    "resultadoPartido": {
      "partido": {
        "local": {
          "nombre": "Gimnasia L.P."
        },
        "visitante": {
          "nombre": "Colon Santa Fe"
        }
      },
      "resultado": {
        "marcadorPorEquipo": {
          "Gimnasia L.P.": 0,
          "Colon Santa Fe": 0
        }
      }
    }
  },
  {
    "resultadoPartido": {
      "partido": {
        "local": {
          "nombre": "Gimnasia L.P."
        },
        "visitante": {
          "nombre": "Barracas Central"
        }
      },
      "resultado": {
        "marcadorPorEquipo": {
          "Gimnasia L.P.": 0,
          "Barracas Central": 1
        }
      }
    }
  },
  {
    "resultadoPartido": {
      "partido": {
        "local": {
          "nombre": "Gimnasia L.P."
        },
        "visitante": {
          "nombre": "Instituto Cordoba"
        }
      },
      "resultado": {
        "marcadorPorEquipo": {
          "Gimnasia L.P.": 2,
          "Instituto Cordoba": 0
        }
      }
    }
  },
  {
    "resultadoPartido": {
      "partido": {
        "local": {
          "nombre": "Gimnasia L.P."
        },
        "visitante": {
          "nombre": "Banfield"
        }
      },
      "resultado": {
        "marcadorPorEquipo": {
          "Gimnasia L.P.": 0,
          "Banfield": 0
        }
      }
    }
  },
  {
    "resultadoPartido": {
      "partido": {
        "local": {
          "nombre": "Defensa Y Justicia"
        },
        "visitante": {
          "nombre": "Gimnasia L.P."
        }
      },
      "resultado": {
        "marcadorPorEquipo": {
          "Defensa Y Justicia": 2,
          "Gimnasia L.P.": 0
        }
      }
    }
  },
  {
    "resultadoPartido": {
      "partido": {
        "local": {
          "nombre": "Gimnasia L.P."
        },
        "visitante": {
          "nombre": "Velez Sarsfield"
        }
      },
      "resultado": {
        "marcadorPorEquipo": {
          "Gimnasia L.P.": 1,
          "Velez Sarsfield": 3
        }
      }
    }
  }
]